aiobp/__init__.py
aiobp/py.typed
aiobp/runner.py
aiobp/task.py
aiobp/aiohttp/__init__.py
aiobp/aiohttp/provider.py
aiobp/config/__init__.py
aiobp/config/conf.py
aiobp/config/exceptions.py
aiobp/config/json.py
aiobp/config/yaml.py
aiobp/logging/__init__.py
aiobp/logging/custom.py
aiobp/logging/log.py
aiobp-1.1.0.dist-info/METADATA
aiobp-1.1.0.dist-info/WHEEL
aiobp-1.1.0.dist-info/top_level.txt
aiobp-1.1.0.dist-info/RECORD
