Metadata-Version: 2.4
Name: aiobp
Version: 1.1.0
Summary: Boilerplate for asyncio service
Author-email: "INSOFT s.r.o." <helpdesk@insoft.cz>
License-Expression: MIT
Requires-Python: >=3.9
Provides-Extra: logging
Requires-Dist: msgspec>=0.19.0; extra == "logging"
Provides-Extra: logging-yaml
Requires-Dist: pyyaml>=6.0.2; extra == "logging-yaml"
Provides-Extra: logging-otel
Requires-Dist: opentelemetry-sdk>=1.20.0; extra == "logging-otel"
Requires-Dist: opentelemetry-exporter-otlp-proto-grpc>=1.20.0; extra == "logging-otel"
